cherminal/__init__.py
cherminal/cherminal.py
cherminal/templates/index.html
cherminal/templates/unauthorized.html
cherminal-0.1.1.dist-info/METADATA
cherminal-0.1.1.dist-info/WHEEL
cherminal-0.1.1.dist-info/entry_points.txt
cherminal-0.1.1.dist-info/top_level.txt
cherminal-0.1.1.dist-info/RECORD
